.gitignore
LICENSE
README
TODO.md
setup.py
ardrone/__init__.py
ardrone/at.py
ardrone/client.py
ardrone/constant.py
ardrone/drone.py
ardrone/navdata.py
ardrone/network.py
ardrone/video.c
ardrone.egg-info/PKG-INFO
ardrone.egg-info/SOURCES.txt
ardrone.egg-info/dependency_links.txt
ardrone.egg-info/top_level.txt