Metadata-Version: 1.0
Name: ardrone
Version: 0.2.1
Summary: A Python library for controlling the Parrot AR.Drone 2.0 over a network
Home-page: https://github.com/fkmclane/python-ardrone
Author: Foster McLane
Author-email: fkmclane@gmail.com
License: MIT
Platform: UNKNOWN
